algorithms/__init__.py
algorithms/cp.py
algorithms/tucker.py
base/__init__.py
base/config.py
base/decoder.py
base/encoder.py
base/tdv.py
base/util.py
pyvidcompress-0.0.5.dist-info/METADATA
pyvidcompress-0.0.5.dist-info/WHEEL
pyvidcompress-0.0.5.dist-info/top_level.txt
pyvidcompress-0.0.5.dist-info/RECORD
