Metadata-Version: 2.1
Name: pyvidcompress
Version: 0.0.5
Summary: Tensor decomposition based video compression library for CPUs and GPUs
Home-page: https://github.com/chathurawidanage/pyvidcompress
Author: Dimuthu Upeksha, Chathura Widanage
Author-email: dimuthu.upeksha2@gmail.com, chathurawidanage@gmail.com
License: UNKNOWN
Platform: UNKNOWN
Classifier: Programming Language :: Python :: 3
Classifier: License :: OSI Approved :: Apache Software License
Classifier: Operating System :: OS Independent
Requires-Python: >=3.7
Requires-Dist: cloudpickle
Requires-Dist: matplotlib
Requires-Dist: numpy
Requires-Dist: opencv-python
Requires-Dist: scikit-video
Requires-Dist: tensorly
Requires-Dist: torch
